[
  {
    "id": "2008.1",
    "caption": "I'm getting nervous I wish you would come home",
    "date": "2008-12-19",
    "img": "imgettingnervousiwishyouwouldcomehome.png",
    "key": "imgettingnervousiwishyouwouldcomehome",
    "title": "I'm getting nervous I wish you would come home"
  },
  {
    "id": "2008.2",
    "caption": "I am sorry I didn't kiss you",
    "date": "2008-12-19",
    "img": "iamsorryididntkissyou.png",
    "key": "iamsorryididntkissyou",
    "title": "I am sorry I didn't kiss you"
  },
  {
    "id": "2008.3",
    "caption": "My mom told me, God is punishing me...",
    "date": "2008-12-18",
    "img": "mymomtoldmegodispunishingme.jpg",
    "key": "mymomtoldmegodispunishingme",
    "title": "My mom told me, God is punishing me..."
  },
  {
    "id": "2008.4",
    "caption": "He destroyed his future",
    "date": "2008-12-18",
    "img": "hedestroyedhisfuture.jpg",
    "key": "hedestroyedhisfuture",
    "title": "He destroyed his future"
  },
  {
    "id": "2008.5",
    "caption": "It was broken before I got here",
    "date": "2008-12-18",
    "img": "itwasbrokenbeforeigothere.jpg",
    "key": "itwasbrokenbeforeigothere",
    "title": "It was broken before I got here"
  },
  {
    "id": "2008.6",
    "caption": "don't stop",
    "date": "2008-12-18",
    "img": "dontstop.jpg",
    "key": "dontstop",
    "title": "don't stop"
  },
  {
    "id": "2008.7",
    "caption": "please come home",
    "date": "2008-12-18",
    "img": "pleasecomehome.jpg",
    "key": "pleasecomehome",
    "title": "please come home"
  },
  {
    "id": "2008.8",
    "caption": "My life would be much easier if I could read your mind",
    "date": "2008-12-18",
    "img": "mylifewouldbemucheasier.jpg",
    "key": "mylifewouldbemucheasier",
    "title": "My life would be much easier if I could read your mind"
  },
  {
    "id": "2008.9",
    "caption": "That was a disappointment",
    "date": "2008-12-18",
    "img": "thatwasadisappointment.jpg",
    "key": "thatwasadisappointment",
    "title": "That was a disappointment"
  },
  {
    "id": "2008.10",
    "caption": "At the time I thought it was a good idea to be chained to this monster",
    "date": "2008-12-18",
    "img": "atthetime.jpg",
    "key": "atthetime",
    "title": "At the time I thought it was a good idea to be chained to this monster"
  },
  {
    "id": "2008.11",
    "caption": "I like the fuzzy ones",
    "date": "2008-12-16",
    "img": "ilikethefuzzyones.png",
    "key": "ilikethefuzzyones",
    "title": "I like the fuzzy ones"
  },
  {
    "id": "2008.12",
    "caption": "What's wrong with him?",
    "date": "2008-12-16",
    "img": "whatswrongwithhim.png",
    "key": "whatswrongwithhim",
    "title": "What's wrong with him?"
  },
  {
    "id": "2008.13",
    "caption": "What are you still doing here?",
    "date": "2008-12-15",
    "img": "whatareyoustilldoinghere.png",
    "key": "whatareyoustilldoinghere",
    "title": "What are you still doing here?"
  },
  {
    "id": "2008.14",
    "caption": "I can't live with this thing",
    "date": "2008-12-15",
    "img": "icantlivewiththisthing.png",
    "key": "icantlivewiththisthing",
    "title": "I can't live with this thing"
  },
  {
    "id": "2008.15",
    "caption": "Is there a problem here?",
    "date": "2008-12-12",
    "img": "isthereaproblemhere.jpg",
    "key": "isthereaproblemhere",
    "title": "Is there a problem here?"
  },
  {
    "id": "2008.16",
    "caption": "I was hoping you would notice",
    "date": "2008-12-12",
    "img": "iwashopingyouwouldnotice.jpg",
    "key": "iwashopingyouwouldnotice",
    "title": "I was hoping you would notice"
  },
  {
    "id": "2008.17",
    "caption": "please don't take this place away from me",
    "date": "2008-12-12",
    "img": "pleasedonttakethisplaceawayfromme.jpg",
    "key": "pleasedonttakethisplaceawayfromme",
    "title": "please don't take this place away from me"
  },
  {
    "id": "2008.18",
    "caption": "Don't stop believin'",
    "date": "2008-12-11",
    "img": "dontstopbelievin.jpg",
    "key": "dontstopbelievin",
    "title": "Don't stop believin'"
  },
  {
    "id": "2008.19",
    "caption": "I've got five",
    "date": "2008-12-11",
    "img": "ivegotfive.jpg",
    "key": "ivegotfive",
    "title": "I've got five"
  },
  {
    "id": "2008.20",
    "caption": "I've thought about you ever day since we met, 738 days and counting...",
    "date": "2008-12-11",
    "img": "ivethoughtaboutyou.jpg",
    "key": "ivethoughtaboutyou",
    "title": "I've thought about you ever day since we met, 738 days and counting..."
  },
  {
    "id": "2008.21",
    "caption": "Look up more",
    "date": "2008-12-11",
    "img": "lookupmore.jpg",
    "key": "lookupmore",
    "title": "Look up more"
  },
  {
    "id": "2008.22",
    "caption": "Happy Birthday",
    "date": "2008-12-10",
    "img": "happybirthday.png",
    "key": "happybirthday",
    "title": "Happy Birthday"
  },
  {
    "id": "2008.23",
    "caption": "I'll do it if you'll do it",
    "date": "2008-12-10",
    "img": "illdoitifyoulldoit.gif",
    "key": "illdoitifyoulldoit",
    "title": "I'll do it if you'll do it"
  },
  {
    "id": "2008.24",
    "caption": "I need a vacation",
    "date": "2008-12-09",
    "img": "ineedavacation.jpg",
    "key": "ineedavacation",
    "title": "I need a vacation"
  },
  {
    "id": "2008.25",
    "caption": "What do you want me to say",
    "date": "2008-12-09",
    "img": "whatdoyouwantmetosay.jpg",
    "key": "whatdoyouwantmetosay",
    "title": "What do you want me to say"
  },
  {
    "id": "2008.26",
    "caption": "It's all downhill from here",
    "date": "2008-12-09",
    "img": "itsalldownhillfromhere.jpg",
    "key": "itsalldownhillfromhere",
    "title": "It's all downhill from here"
  },
  {
    "id": "2008.27",
    "caption": "I'll never finish",
    "date": "2008-12-08",
    "img": "illneverfinish.png",
    "key": "illneverfinish",
    "title": "I'll never finish"
  },
  {
    "id": "2008.28",
    "caption": "We have something special",
    "date": "2008-12-08",
    "img": "wehavesomethingspecial.png",
    "key": "wehavesomethingspecial",
    "title": "We have something special"
  },
  {
    "id": "2008.29",
    "caption": "I'm not like the other girls",
    "date": "2008-12-05",
    "img": "imnotliketheothergirls.jpg",
    "key": "imnotliketheothergirls",
    "title": "I'm not like the other girls"
  },
  {
    "id": "2008.30",
    "caption": "I hope you're happy when I die",
    "date": "2008-12-05",
    "img": "ihopeyourehappywhenidie.jpg",
    "key": "ihopeyourehappywhenidie",
    "title": "I hope you're happy when I die"
  },
  {
    "id": "2008.31",
    "caption": "This is the best birthday present ever",
    "date": "2008-12-05",
    "img": "thisisthebestbirthdaypresentever.jpg",
    "key": "thisisthebestbirthdaypresentever",
    "title": "This is the best birthday present ever"
  },
  {
    "id": "2008.32",
    "caption": "I got new shoes",
    "date": "2008-12-05",
    "img": "igotnewshoes.jpg",
    "key": "igotnewshoes",
    "title": "I got new shoes"
  },
  {
    "id": "2008.33",
    "caption": "I live alone",
    "date": "2008-12-04",
    "img": "ilivealone.png",
    "key": "ilivealone",
    "title": "I live alone"
  },
  {
    "id": "2008.34",
    "caption": "This is Blasphemy!",
    "date": "2008-12-04",
    "img": "thisisblasphemy.gif",
    "key": "thisisblasphemy",
    "title": "This is Blasphemy!"
  },
  {
    "id": "2008.35",
    "caption": "just going for a short walk",
    "date": "2008-12-03",
    "img": "justgoingforashortwalk.png",
    "key": "justgoingforashortwalk",
    "title": "just going for a short walk"
  },
  {
    "id": "2008.36",
    "caption": "Why didn't you love me back",
    "date": "2008-12-03",
    "img": "whydidntyoulovemeback.png",
    "key": "whydidntyoulovemeback",
    "title": "Why didn't you love me back"
  },
  {
    "id": "2008.37",
    "caption": "You won't use this, I know",
    "date": "2008-12-02",
    "img": "youwontusethisiknow.jpg",
    "key": "youwontusethisiknow",
    "title": "You won't use this, I know"
  },
  {
    "id": "2008.38",
    "caption": "Sometimes I lie",
    "date": "2008-12-02",
    "img": "sometimesilie.jpg",
    "key": "sometimesilie",
    "title": "Sometimes I lie"
  },
  {
    "id": "2008.39",
    "caption": "God bless you",
    "date": "2008-12-02",
    "img": "godblessyou.jpg",
    "key": "godblessyou",
    "title": "God bless you"
  },
  {
    "id": "2008.40",
    "caption": "Maybe this time it'll happen",
    "date": "2008-12-02",
    "img": "maybethistimeitllhappen.jpg",
    "key": "maybethistimeitllhappen",
    "title": "Maybe this time it'll happen"
  },
  {
    "id": "2008.41",
    "caption": "I don't see you",
    "date": "2008-12-02",
    "img": "idontseeyou.jpg",
    "key": "idontseeyou",
    "title": "I don't see you"
  },
  {
    "id": "2008.42",
    "caption": "I found your radio",
    "date": "2008-12-01",
    "img": "ifoundyourradio.jpg",
    "key": "ifoundyourradio",
    "title": "I found your radio"
  },
  {
    "id": "2008.43",
    "caption": "It's only complicated when you make it complicated",
    "date": "2008-12-01",
    "img": "itsonlycomplicatedwhenyoumakeitcomplicated.jpg",
    "key": "itsonlycomplicatedwhenyoumakeitcomplicated",
    "title": "It's only complicated when you make it complicated"
  },
  {
    "id": "2008.44",
    "caption": "I've been trying for years",
    "date": "2008-12-01",
    "img": "ivebeentryingforyears.jpg",
    "key": "ivebeentryingforyears",
    "title": "I've been trying for years"
  },
  {
    "id": "2008.45",
    "caption": "Listen, I'll be right here waiting...",
    "date": "2008-12-01",
    "img": "listenillberightherewaiting.jpg",
    "key": "listenillberightherewaiting",
    "title": "Listen, I'll be right here waiting..."
  },
  {
    "id": "2008.46",
    "caption": "tell me something extra nice",
    "date": "2008-12-01",
    "img": "tellmesomethingextranice.jpg",
    "key": "tellmesomethingextranice",
    "title": "tell me something extra nice"
  },
  {
    "id": "2008.47",
    "caption": "We are finally married",
    "date": "2008-12-01",
    "img": "wearefinallymarried.jpg",
    "key": "wearefinallymarried",
    "title": "We are finally married"
  },
  {
    "id": "2008.48",
    "caption": "you're too predictable",
    "date": "2008-12-01",
    "img": "youretoopredictable.jpg",
    "key": "youretoopredictable",
    "title": "you're too predictable"
  },
  {
    "id": "2008.49",
    "caption": "I only love you when I'm drunk",
    "date": "2008-11-26",
    "img": "ionlyloveyouwhenimdrunk.jpg",
    "key": "ionlyloveyouwhenimdrunk",
    "title": "I only love you when I'm drunk"
  },
  {
    "id": "2008.50",
    "caption": "I don't have a headache",
    "date": "2008-11-26",
    "img": "idonthaveaheadache.jpg",
    "key": "idonthaveaheadache",
    "title": "I don't have a headache"
  },
  {
    "id": "2008.51",
    "caption": "No one can know",
    "date": "2008-11-24",
    "img": "noonecanknow.png",
    "key": "noonecanknow",
    "title": "No one can know"
  },
  {
    "id": "2008.52",
    "caption": "Stuck in the clouds",
    "date": "2008-11-24",
    "img": "stuckintheclouds.png",
    "key": "stuckintheclouds",
    "title": "Stuck in the clouds"
  }
]
