
[
  {
    "id": "2007.313",
    "date": "2007-12-27",
    "img": "thoughtthiswasagoodstart.png",
    "key": "thoughtthiswasagoodstart",
    "title": "thought this was a good start"
  },
  {
    "id": "2007.312",
    "date": "2007-12-27",
    "img": "firstdayofmylife.png",
    "key": "firstdayofmylife",
    "title": "first day of my life"
  },
  {
    "id": "2007.311",
    "date": "2007-12-20",
    "img": "youremyfavoritescientist.png",
    "key": "youremyfavoritescientist",
    "title": "You're my favorite scientist"
  },
  {
    "id": "2007.310",
    "date": "2007-12-20",
    "img": "whycantitouchit.png",
    "key": "whycantitouchit",
    "title": "Why can't I touch it?"
  },
  {
    "id": "2007.309",
    "date": "2007-12-19",
    "img": "yesterdayiwashuman.png",
    "key": "yesterdayiwashuman",
    "title": "yesterday I was human"
  },
  {
    "id": "2007.308",
    "date": "2007-12-19",
    "img": "sometimesismile.png",
    "key": "sometimesismile",
    "title": "sometimes I smile"
  },
  {
    "id": "2007.307",
    "date": "2007-12-18",
    "img": "imsick.png",
    "key": "imsick",
    "title": "I'm sick"
  },
  {
    "id": "2007.306",
    "date": "2007-12-18",
    "img": "nowimlost.png",
    "key": "nowimlost",
    "title": "now I'm lost"
  },
  {
    "id": "2007.305",
    "date": "2007-12-17",
    "img": "whycantwetalklikeweusedto.png",
    "key": "whycantwetalklikeweusedto",
    "title": "Why can't we talk like we used to?"
  },
  {
    "id": "2007.304",
    "date": "2007-12-17",
    "img": "imaskingfortrouble.png",
    "key": "imaskingfortrouble",
    "title": "I'm asking for trouble"
  },
  {
    "id": "2007.303",
    "date": "2007-12-14",
    "img": "myfavoriteistheblueone.png",
    "key": "myfavoriteistheblueone",
    "title": "My favorite is the blue one"
  },
  {
    "id": "2007.302",
    "date": "2007-12-14",
    "img": "yeahyouforgotagain.png",
    "key": "yeahyouforgotagain",
    "title": "yeah, you forgot again"
  },
  {
    "id": "2007.301",
    "date": "2007-12-13",
    "img": "ihatechristmas.png",
    "key": "ihatechristmas",
    "title": "I hate Christmas"
  },
  {
    "id": "2007.300",
    "date": "2007-12-13",
    "img": "ourlittlesecret.png",
    "key": "ourlittlesecret",
    "title": "our little secret"
  },
  {
    "id": "2007.299",
    "date": "2007-12-12",
    "img": "itstheonlywayoutofhere.png",
    "key": "itstheonlywayoutofhere",
    "title": "it's the only way out of here"
  },
  {
    "id": "2007.298",
    "date": "2007-12-12",
    "img": "imakecoffee.png",
    "key": "imakecoffee",
    "title": "I make coffee"
  },
  {
    "id": "2007.297",
    "date": "2007-12-12",
    "img": "iloveyoubutidontknowifibelieveyou.png",
    "key": "iloveyoubutidontknowifibelieveyou",
    "title": "I love you, but I don't know if I believe you"
  },
  {
    "id": "2007.296",
    "date": "2007-12-11",
    "img": "whenilookup.png",
    "key": "whenilookup",
    "title": "when I look up I feel like I am falling, when I look down I feel like I am flying"
  },
  {
    "id": "2007.295",
    "date": "2007-12-11",
    "img": "aminotcuteenough.png",
    "key": "aminotcuteenough",
    "title": "am I not cute enough?"
  },
  {
    "id": "2007.294",
    "date": "2007-12-10",
    "img": "areyousureyoupushedtherightbutton.png",
    "key": "areyousureyoupushedtherightbutton",
    "title": "are you sure you pushed the right button?"
  },
  {
    "id": "2007.293",
    "date": "2007-12-10",
    "img": "youvesureletyourselfgo.png",
    "key": "youvesureletyourselfgo",
    "title": "you've sure let yourself go"
  },
  {
    "id": "2007.292",
    "date": "2007-12-10",
    "img": "imjustalittlesoutherngirl.png",
    "key": "imjustalittlesoutherngirl",
    "title": "I'm just a little southern girl"
  },
  {
    "id": "2007.291",
    "date": "2007-12-07",
    "img": "demonofgravity.png",
    "key": "demonofgravity",
    "title": "demon of gravity"
  },
  {
    "id": "2007.290",
    "date": "2007-12-07",
    "img": "ithoughtitwouldbebigger.png",
    "key": "ithoughtitwouldbebigger",
    "title": "I thought it would be bigger"
  },
  {
    "id": "2007.289",
    "date": "2007-12-06",
    "img": "icouldtellyouwerebeautiful.png",
    "key": "icouldtellyouwerebeautiful",
    "title": "I could tell you were beautiful by the look on your face"
  },
  {
    "id": "2007.288",
    "date": "2007-12-06",
    "img": "iwonderifyoumissmeasmuchasimissyou.png",
    "key": "iwonderifyoumissmeasmuchasimissyou",
    "title": "i wonder if you miss me as much as I miss you?"
  },
  {
    "id": "2007.287",
    "date": "2007-12-06",
    "img": "isumad.png",
    "key": "isumad",
    "title": "Is U mad?"
  },
  {
    "id": "2007.286",
    "date": "2007-12-05",
    "img": "sheismysunshine.png",
    "key": "sheismysunshine",
    "title": "She is my sunshine"
  },
  {
    "id": "2007.285",
    "date": "2007-12-05",
    "img": "youdroppedthis.png",
    "key": "youdroppedthis",
    "title": "you dropped this"
  },
  {
    "id": "2007.284",
    "date": "2007-12-05",
    "img": "pleasedontcall.png",
    "key": "pleasedontcall",
    "title": "please don't call"
  },
  {
    "id": "2007.283",
    "date": "2007-12-04",
    "img": "ifeellikealostmoon.png",
    "key": "ifeellikealostmoon",
    "title": "i feel like a lost moon... my planet destroyed by some cataclysmic disaster... i continue into desolation, circling in a tight little familiar orbit around the empty space left behind, ignoring the laws of gravity and refusing to believe that it is gone."
  },
  {
    "id": "2007.282",
    "date": "2007-12-04",
    "img": "sailorinthedesert.png",
    "key": "sailorinthedesert",
    "title": "Sailor in the desert"
  },
  {
    "id": "2007.281",
    "date": "2007-12-03",
    "img": "imnotreallyhere.png",
    "key": "imnotreallyhere",
    "title": "I'm not really here"
  },
  {
    "id": "2007.280",
    "date": "2007-12-03",
    "img": "thesedaisiesareovercooked.png",
    "key": "thesedaisiesareovercooked",
    "title": "these daisies are overcooked"
  },
  {
    "id": "2007.279",
    "date": "2007-11-30",
    "img": "icantelltheressomethinggoingonhere.png",
    "key": "icantelltheressomethinggoingonhere",
    "title": "I can tell there's something going on here"
  },
  {
    "id": "2007.278",
    "date": "2007-11-30",
    "img": "awwwthattrickneverworks.png",
    "key": "awwwthattrickneverworks",
    "title": "awww, that trick never works"
  },
  {
    "id": "2007.277",
    "date": "2007-11-29",
    "img": "theresnoquestionaboutit.png",
    "key": "theresnoquestionaboutit",
    "title": "there's no question about it"
  },
  {
    "id": "2007.276",
    "date": "2007-11-29",
    "img": "wheredidtheyallgo.png",
    "key": "wheredidtheyallgo",
    "title": "where did they all go"
  },
  {
    "id": "2007.275",
    "date": "2007-11-28",
    "img": "iliketobewithyou.png",
    "key": "iliketobewithyou",
    "title": "I like to be with you"
  },
  {
    "id": "2007.274",
    "date": "2007-11-28",
    "img": "itsalwaystoolate.png",
    "key": "itsalwaystoolate",
    "title": "it's always too late"
  },
  {
    "id": "2007.273",
    "date": "2007-11-27",
    "img": "iwantawayoutofthis.png",
    "key": "iwantawayoutofthis",
    "title": "I want a way out of this"
  },
  {
    "id": "2007.272",
    "date": "2007-11-27",
    "img": "godtoldme.png",
    "key": "godtoldme",
    "title": "God told me"
  },
  {
    "id": "2007.271",
    "date": "2007-11-26",
    "img": "idontknowwhoyouthinkiam.png",
    "key": "idontknowwhoyouthinkiam",
    "title": "I don't know who you think I am"
  },
  {
    "id": "2007.270",
    "date": "2007-11-26",
    "img": "iwillneverbelateagain.png",
    "key": "iwillneverbelateagain",
    "title": "I will never be late again"
  },
  {
    "id": "2007.269",
    "date": "2007-11-23",
    "img": "youcouldhavesaidno.png",
    "key": "youcouldhavesaidno",
    "title": "you could have said no"
  },
  {
    "id": "2007.268",
    "date": "2007-11-23",
    "img": "iwishicouldstopthinkingaboutyou.png",
    "key": "iwishicouldstopthinkingaboutyou",
    "title": "I wish I could stop thinking about you"
  },
  {
    "id": "2007.267",
    "date": "2007-11-21",
    "img": "itswhatido.png",
    "key": "itswhatido",
    "title": "it's what i DO"
  },
  {
    "id": "2007.266",
    "date": "2007-11-21",
    "img": "iamgoingtokillmyselftomorrow.png",
    "key": "iamgoingtokillmyselftomorrow",
    "title": "I am going to kill myself tomorrow"
  },
  {
    "id": "2007.265",
    "date": "2007-11-20",
    "img": "ithinkikilledmyplant.png",
    "key": "ithinkikilledmyplant",
    "title": "I think I killed my plant"
  },
  {
    "id": "2007.264",
    "date": "2007-11-20",
    "img": "ilovepigs---.png",
    "key": "ilovepigs---",
    "title": "I love pigs!!!"
  },
  {
    "id": "2007.263",
    "date": "2007-11-19",
    "img": "youmakemecool.png",
    "key": "youmakemecool",
    "title": "you make me cool"
  },
  {
    "id": "2007.262",
    "date": "2007-11-19",
    "img": "ordidijustblowyourmind.png",
    "key": "ordidijustblowyourmind",
    "title": "Or did I just blow your mind?"
  },
  {
    "id": "2007.261",
    "date": "2007-11-16",
    "img": "igetnervousincars.png",
    "key": "igetnervousincars",
    "title": "I get nervous in cars"
  },
  {
    "id": "2007.260",
    "date": "2007-11-16",
    "img": "excusemesirwouldyoumindtellingmewhattimeitis.png",
    "key": "excusemesirwouldyoumindtellingmewhattimeitis",
    "title": "excuse me sir would you mind telling me what time it is?"
  },
  {
    "id": "2007.259",
    "date": "2007-11-15",
    "img": "ithinkiamsick.png",
    "key": "ithinkiamsick",
    "title": "I think I am sick"
  },
  {
    "id": "2007.258",
    "date": "2007-11-15",
    "img": "iateyourrainbow.png",
    "key": "iateyourrainbow",
    "title": "I ate your rainbow"
  },
  {
    "id": "2007.257",
    "date": "2007-11-15",
    "img": "itsbeenfourdaysnow.png",
    "key": "itsbeenfourdaysnow",
    "title": "it's been four days now"
  },
  {
    "id": "2007.256",
    "date": "2007-11-14",
    "img": "thedoctorsaiditsnotchickenpox.png",
    "key": "thedoctorsaiditsnotchickenpox",
    "title": "The Doctor said it's not chicken pox"
  },
  {
    "id": "2007.255",
    "date": "2007-11-14",
    "img": "wordscanspoileverything.png",
    "key": "wordscanspoileverything",
    "title": "words can spoil everything"
  },
  {
    "id": "2007.254",
    "date": "2007-11-13",
    "img": "iwishiunderstood-2.png",
    "key": "iwishiunderstood-2",
    "title": "I wish I understood"
  },
  {
    "id": "2007.253",
    "date": "2007-11-13",
    "img": "itsokihaveanother.png",
    "key": "itsokihaveanother",
    "title": "It's ok I have another"
  },
  {
    "id": "2007.252",
    "date": "2007-11-12",
    "img": "iwishihadadragon.png",
    "key": "iwishihadadragon",
    "title": "I wish I had a dragon"
  },
  {
    "id": "2007.251",
    "date": "2007-11-12",
    "img": "iwishicouldtakehimwithme.png",
    "key": "iwishicouldtakehimwithme",
    "title": "I wish I could take him with me"
  },
  {
    "id": "2007.250",
    "date": "2007-11-09",
    "img": "weshareabrain.png",
    "key": "weshareabrain",
    "title": "we share a brain"
  },
  {
    "id": "2007.249",
    "date": "2007-11-09",
    "img": "iwillneverforgethowyouhurtme.png",
    "key": "iwillneverforgethowyouhurtme",
    "title": "I will never forget how you hurt me"
  },
  {
    "id": "2007.248",
    "date": "2007-11-08",
    "img": "ineedtomove.png",
    "key": "ineedtomove",
    "title": "I need to move"
  },
  {
    "id": "2007.247",
    "date": "2007-11-08",
    "img": "onofthesedaysiamgoingtocutyouintolittlepieces.png",
    "key": "onofthesedaysiamgoingtocutyouintolittlepieces",
    "title": "One of these days I am going to cut you into little pieces"
  },
  {
    "id": "2007.246",
    "date": "2007-11-07",
    "img": "iwaswrong.png",
    "key": "iwaswrong",
    "title": "I was wrong"
  },
  {
    "id": "2007.245",
    "date": "2007-11-07",
    "img": "outsidetheuniverse.png",
    "key": "outsidetheuniverse",
    "title": "outside the universe"
  },
  {
    "id": "2007.244",
    "date": "2007-11-06",
    "img": "icouldendtheworld.png",
    "key": "icouldendtheworld",
    "title": "I could end the world"
  },
  {
    "id": "2007.243",
    "date": "2007-11-06",
    "img": "fakeplastictrees.png",
    "key": "fakeplastictrees",
    "title": "fake plastic trees"
  },
  {
    "id": "2007.242",
    "date": "2007-11-05",
    "img": "ihaveideas.png",
    "key": "ihaveideas",
    "title": "I have ideas"
  },
  {
    "id": "2007.241",
    "date": "2007-11-05",
    "img": "areyougoingtoeatthat.png",
    "key": "areyougoingtoeatthat",
    "title": "are you going to eat that?"
  },
  {
    "id": "2007.240",
    "date": "2007-11-05",
    "img": "icantbelievehowluckyiam.png",
    "key": "icantbelievehowluckyiam",
    "title": "I can't believe how lucky I am"
  },
  {
    "id": "2007.239",
    "date": "2007-11-02",
    "img": "ilostmyglassesinthepacificocean.png",
    "key": "ilostmyglassesinthepacificocean",
    "title": "I lost my glasses in the pacific ocean"
  },
  {
    "id": "2007.238",
    "date": "2007-11-02",
    "img": "takecare.png",
    "key": "takecare",
    "title": "Take Care"
  },
  {
    "id": "2007.237",
    "date": "2007-11-01",
    "img": "lovingyouhasalwayshurt.png",
    "key": "lovingyouhasalwayshurt",
    "title": "Loving you has always hurt"
  },
  {
    "id": "2007.236",
    "date": "2007-11-01",
    "img": "icantsleepwhenyouarentnearme.png",
    "key": "icantsleepwhenyouarentnearme",
    "title": "I can't sleep when you aren't near me"
  },
  {
    "id": "2007.235",
    "date": "2007-10-31",
    "img": "wedliketointroduceyoutothestaff.png",
    "key": "wedliketointroduceyoutothestaff",
    "title": "We'd like to introduce you to the staff"
  },
  {
    "id": "2007.234",
    "date": "2007-10-31",
    "img": "aquietmomentalone.png",
    "key": "aquietmomentalone",
    "title": "A quiet moment alone"
  },
  {
    "id": "2007.233",
    "date": "2007-10-30",
    "img": "youdontwantanexplanationtrustme.png",
    "key": "youdontwantanexplanationtrustme",
    "title": "You don't want an explanation, trust me."
  },
  {
    "id": "2007.232",
    "date": "2007-10-30",
    "img": "ithinkaboutyoumorethanyourealize.png",
    "key": "ithinkaboutyoumorethanyourealize",
    "title": "I think about you more than you realize"
  },
  {
    "id": "2007.231",
    "date": "2007-10-29",
    "img": "thosefourguyshelpedmealot.png",
    "key": "thosefourguyshelpedmealot",
    "title": "Those Four Guys Helped Me a Lot"
  },
  {
    "id": "2007.230",
    "date": "2007-10-29",
    "img": "ihaveathingfordoves.png",
    "key": "ihaveathingfordoves",
    "title": "I have a thing for doves"
  },
  {
    "id": "2007.229",
    "date": "2007-10-29",
    "img": "avindictiverampage.png",
    "key": "avindictiverampage",
    "title": "a vindictive rampage"
  },
  {
    "id": "2007.228",
    "date": "2007-10-29",
    "img": "iwishyouwouldgetoutofmyhead.png",
    "key": "iwishyouwouldgetoutofmyhead",
    "title": "I wish you would get out of my head"
  },
  {
    "id": "2007.227",
    "date": "2007-10-26",
    "img": "iwanttoplaythepiano.png",
    "key": "iwanttoplaythepiano",
    "title": "I want to play the piano"
  },
  {
    "id": "2007.226",
    "date": "2007-10-26",
    "img": "iwanttoholdyourhand.png",
    "key": "iwanttoholdyourhand",
    "title": "I want to hold your hand"
  },
  {
    "id": "2007.225",
    "date": "2007-10-25",
    "img": "ihatemyjob.png",
    "key": "ihatemyjob",
    "title": "I hate my job"
  },
  {
    "id": "2007.224",
    "date": "2007-10-25",
    "img": "sinceyourgonetheresnoplaceicancallhome.png",
    "key": "sinceyourgonetheresnoplaceicancallhome",
    "title": "since you're gone there's no place i can call home"
  },
  {
    "id": "2007.223",
    "date": "2007-10-25",
    "img": "songstuckinmyhead.png",
    "key": "songstuckinmyhead",
    "title": "song stuck in my head"
  },
  {
    "id": "2007.222",
    "date": "2007-10-24",
    "img": "whatcanisay.png",
    "key": "whatcanisay",
    "title": "What can I say?"
  },
  {
    "id": "2007.221",
    "date": "2007-10-24",
    "img": "nomorelittlebabies.png",
    "key": "nomorelittlebabies",
    "title": "No more little babies"
  },
  {
    "id": "2007.220",
    "date": "2007-10-23",
    "img": "iwillfightyou.png",
    "key": "iwillfightyou",
    "title": "I will fight you"
  },
  {
    "id": "2007.219",
    "date": "2007-10-23",
    "img": "icantkeeppretendingthateverythingisalright.png",
    "key": "icantkeeppretendingthateverythingisalright",
    "title": "I can't keep pretending that everything is alright"
  },
  {
    "id": "2007.218",
    "date": "2007-10-23",
    "img": "ifonlyitoldyousooner.png",
    "key": "ifonlyitoldyousooner",
    "title": "If only I told you sooner"
  },
  {
    "id": "2007.217",
    "date": "2007-10-22",
    "img": "shesmyflame.png",
    "key": "shesmyflame",
    "title": "She's my flame"
  },
  {
    "id": "2007.216",
    "date": "2007-10-22",
    "img": "250milesfaraway.png",
    "key": "250milesfaraway",
    "title": "250 miles far away"
  },
  {
    "id": "2007.215",
    "date": "2007-10-22",
    "img": "imgoingtoneedthose.png",
    "key": "imgoingtoneedthose",
    "title": "I'm going to need those"
  },
  {
    "id": "2007.214",
    "date": "2007-10-19",
    "img": "nooneunderstandsme.png",
    "key": "nooneunderstandsme",
    "title": "no one understands me"
  },
  {
    "id": "2007.213",
    "date": "2007-10-19",
    "img": "eventhebasicsareexpensive.png",
    "key": "eventhebasicsareexpensive",
    "title": "even the basics are expensive"
  },
  {
    "id": "2007.212",
    "date": "2007-10-19",
    "img": "theydontknowwhatiwant.png",
    "key": "theydontknowwhatiwant",
    "title": "they don't know what I want"
  },
  {
    "id": "2007.211",
    "date": "2007-10-18",
    "img": "whatifgodwasoneofushuh.png",
    "key": "whatifgodwasoneofushuh",
    "title": "What IF god were one of us, huh?"
  },
  {
    "id": "2007.210",
    "date": "2007-10-18",
    "img": "imatool.png",
    "key": "imatool",
    "title": "I'm a tool"
  },
  {
    "id": "2007.209",
    "date": "2007-10-18",
    "img": "thecusineismonotonous.png",
    "key": "thecusineismonotonous",
    "title": "the cuisine is monotonous"
  },
  {
    "id": "2007.208",
    "date": "2007-10-17",
    "img": "weevengotourownsecrethandshake.png",
    "key": "weevengotourownsecrethandshake",
    "title": "we even got our own secret handshake"
  },
  {
    "id": "2007.207",
    "date": "2007-10-17",
    "img": "imonanislandyouareonabiggerisland.png",
    "key": "imonanislandyouareonabiggerisland",
    "title": "I'm on an island you are on a bigger island"
  },
  {
    "id": "2007.206",
    "date": "2007-10-16",
    "img": "pleasedrinkresponsibly.png",
    "key": "pleasedrinkresponsibly",
    "title": "please drink responsibly"
  },
  {
    "id": "2007.205",
    "date": "2007-10-16",
    "img": "imrepeatingallthesamemistakes.png",
    "key": "imrepeatingallthesamemistakes",
    "title": "I'm repeating all the same mistakes"
  },
  {
    "id": "2007.204",
    "date": "2007-10-16",
    "img": "hedgivenupbeforewestarted.png",
    "key": "hedgivenupbeforewestarted",
    "title": "He'd given up before we started"
  },
  {
    "id": "2007.203",
    "date": "2007-10-15",
    "img": "imaspecialsnowflake.png",
    "key": "imaspecialsnowflake",
    "title": "I'm a special snowflake"
  },
  {
    "id": "2007.202",
    "date": "2007-10-15",
    "img": "iwishyouknewhowifelt.png",
    "key": "iwishyouknewhowifelt",
    "title": "I wish you knew how I felt"
  },
  {
    "id": "2007.201",
    "date": "2007-10-15",
    "img": "iwanttogohome.png",
    "key": "iwanttogohome",
    "title": "I want to go home"
  },
  {
    "id": "2007.200",
    "date": "2007-10-12",
    "img": "ilikedyoubetterwiththemustache.png",
    "key": "ilikedyoubetterwiththemustache",
    "title": "I liked you better with the mustache"
  },
  {
    "id": "2007.199",
    "date": "2007-10-12",
    "img": "imaginationismoreimportantthanknowledge.png",
    "key": "imaginationismoreimportantthanknowledge",
    "title": "imagination is more important than knowledge"
  },
  {
    "id": "2007.198",
    "date": "2007-10-12",
    "img": "whatsinthemiddle.png",
    "key": "whatsinthemiddle",
    "title": "what's in the middle"
  },
  {
    "id": "2007.197",
    "date": "2007-10-11",
    "img": "idrinkteaeverymorning.png",
    "key": "idrinkteaeverymorning",
    "title": "I drink tea every morning"
  },
  {
    "id": "2007.196",
    "date": "2007-10-11",
    "img": "ihatethissubmarine.png",
    "key": "ihatethissubmarine",
    "title": "I hate this submarine"
  },
  {
    "id": "2007.195",
    "date": "2007-10-11",
    "img": "idontwanttolivewithyouanymore.png",
    "key": "idontwanttolivewithyouanymore",
    "title": "I don't want to live with you anymore"
  },
  {
    "id": "2007.194",
    "date": "2007-10-11",
    "img": "thingssomehowgotoutofcontrol.png",
    "key": "thingssomehowgotoutofcontrol",
    "title": "things somehow got out of control"
  },
  {
    "id": "2007.193",
    "date": "2007-10-10",
    "img": "myloveisbroken.png",
    "key": "myloveisbroken",
    "title": "my love is broken"
  },
  {
    "id": "2007.192",
    "date": "2007-10-10",
    "img": "imisshersomuch.png",
    "key": "imisshersomuch",
    "title": "I miss her so much"
  },
  {
    "id": "2007.191",
    "date": "2007-10-09",
    "img": "itsjustkindofcomplicated.png",
    "key": "itsjustkindofcomplicated",
    "title": "it's just kind of complicated"
  },
  {
    "id": "2007.190",
    "date": "2007-10-09",
    "img": "ijustwantedtoknowwhereistoodbutyoutookitthewrongway.png",
    "key": "ijustwantedtoknowwhereistoodbutyoutookitthewrongway",
    "title": "I just wanted to know where I stood, but you took it the wrong way"
  },
  {
    "id": "2007.189",
    "date": "2007-10-09",
    "img": "idontknowwhattodoanymore.png",
    "key": "idontknowwhattodoanymore",
    "title": "I don't know what to do anymore"
  },
  {
    "id": "2007.188",
    "date": "2007-10-08",
    "img": "drawadogcarryingacatplease.png",
    "key": "drawadogcarryingacatplease",
    "title": "draw a dog carrying a cat please"
  },
  {
    "id": "2007.187",
    "date": "2007-10-08",
    "img": "emptyinside.png",
    "key": "emptyinside",
    "title": "empty inside"
  },
  {
    "id": "2007.186",
    "date": "2007-10-05",
    "img": "whyareyougone.png",
    "key": "whyareyougone",
    "title": "why are you gone?"
  },
  {
    "id": "2007.185",
    "date": "2007-10-05",
    "img": "imstandingontheedge.png",
    "key": "imstandingontheedge",
    "title": "I'm standing on the edge"
  },
  {
    "id": "2007.184",
    "date": "2007-10-05",
    "img": "whydidyoucallme.png",
    "key": "whydidyoucallme",
    "title": "Why did you call me???"
  },
  {
    "id": "2007.183",
    "date": "2007-10-04",
    "img": "ifonlyihadknownearlier.png",
    "key": "ifonlyihadknownearlier",
    "title": "If only I had known earlier"
  },
  {
    "id": "2007.182",
    "date": "2007-10-04",
    "img": "theresfuntobehadatahazardouswastefacility.png",
    "key": "theresfuntobehadatahazardouswastefacility",
    "title": "there's fun to be had at the hazardous waste facility"
  },
  {
    "id": "2007.181",
    "date": "2007-10-04",
    "img": "itsbettertobeluckythansmart.png",
    "key": "itsbettertobeluckythansmart",
    "title": "it's better to be lucky than smart"
  },
  {
    "id": "2007.180",
    "date": "2007-10-03",
    "img": "iwanttogoback.gif",
    "key": "iwanttogoback",
    "title": "I want to go back..."
  },
  {
    "id": "2007.179",
    "date": "2007-10-03",
    "img": "amisurethisisme.png",
    "key": "amisurethisisme",
    "title": "am I sure this is me?"
  },
  {
    "id": "2007.178",
    "date": "2007-10-03",
    "img": "smellit.png",
    "key": "smellit",
    "title": "smell it?"
  },
  {
    "id": "2007.177",
    "date": "2007-10-02",
    "img": "imadiver.png",
    "key": "imadiver",
    "title": "I'm a diver"
  },
  {
    "id": "2007.176",
    "date": "2007-10-02",
    "img": "idontmissit.png",
    "key": "idontmissit",
    "title": "I don't miss it"
  },
  {
    "id": "2007.175",
    "date": "2007-10-01",
    "img": "whyareyoustillhere.png",
    "key": "whyareyoustillhere",
    "title": "Why are you still here?"
  },
  {
    "id": "2007.174",
    "date": "2007-10-01",
    "img": "iwishihadseenyoufirst.png",
    "key": "iwishihadseenyoufirst",
    "title": "I wish I had seen you first"
  },
  {
    "id": "2007.173",
    "date": "2007-09-28",
    "img": "iseveryoneagainstme.png",
    "key": "iseveryoneagainstme",
    "title": "Is every one against me?"
  },
  {
    "id": "2007.172",
    "date": "2007-09-28",
    "img": "sleepnownomoretalking.png",
    "key": "sleepnownomoretalking",
    "title": "sleep now, no more talking"
  },
  {
    "id": "2007.171",
    "date": "2007-09-27",
    "img": "mystomachhurts.png",
    "key": "mystomachhurts",
    "title": "my stomach hurts"
  },
  {
    "id": "2007.170",
    "date": "2007-09-27",
    "img": "iwantittorainagain.png",
    "key": "iwantittorainagain",
    "title": "I want it to rain again"
  },
  {
    "id": "2007.169",
    "date": "2007-09-27",
    "img": "amihappywiththisorjustabletoputupwithit.png",
    "key": "amihappywiththisorjustabletoputupwithit",
    "title": "am I happy with this or just able to put up with it?"
  },
  {
    "id": "2007.168",
    "date": "2007-09-26",
    "img": "agiraffewithaknife.png",
    "key": "agiraffewithaknife",
    "title": "a giraffe with a knife"
  },
  {
    "id": "2007.167",
    "date": "2007-09-26",
    "img": "abirdsatonmywindowsilltoday.png",
    "key": "abirdsatonmywindowsilltoday",
    "title": "a bird sat on my window sill today..."
  },
  {
    "id": "2007.166",
    "date": "2007-09-25",
    "img": "thisismylife.png",
    "key": "thisismylife",
    "title": "this is my life"
  },
  {
    "id": "2007.165",
    "date": "2007-09-25",
    "img": "invisibilityorflight.png",
    "key": "invisibilityorflight",
    "title": "invisibility or flight?"
  },
  {
    "id": "2007.164",
    "date": "2007-09-24",
    "img": "doyouremember.png",
    "key": "doyouremember",
    "title": "do you remember?"
  },
  {
    "id": "2007.163",
    "date": "2007-09-24",
    "img": "isthisit.png",
    "key": "isthisit",
    "title": "Is this it?"
  },
  {
    "id": "2007.162",
    "date": "2007-09-24",
    "img": "iwanttostealyourcovers.png",
    "key": "iwanttostealyourcovers",
    "title": "I want to steal your covers"
  },
  {
    "id": "2007.161",
    "date": "2007-09-21",
    "img": "therearesomethingsiregret.png",
    "key": "therearesomethingsiregret",
    "title": "there are somethings I regret"
  },
  {
    "id": "2007.160",
    "date": "2007-09-21",
    "img": "significantlyinsignificant.png",
    "key": "significantlyinsignificant",
    "title": "significantly insignificant"
  },
  {
    "id": "2007.159",
    "date": "2007-09-20",
    "img": "turtlelove.png",
    "key": "turtlelove",
    "title": "turtle love"
  },
  {
    "id": "2007.158",
    "date": "2007-09-20",
    "img": "everytimeisneeze.png",
    "key": "everytimeisneeze",
    "title": "every time I sneeze"
  },
  {
    "id": "2007.157",
    "date": "2007-09-19",
    "img": "ifyouonlyknew.png",
    "key": "ifyouonlyknew",
    "title": "if you only knew"
  },
  {
    "id": "2007.156",
    "date": "2007-09-19",
    "img": "theendofsomething.png",
    "key": "theendofsomething",
    "title": "the end of something"
  },
  {
    "id": "2007.155",
    "date": "2007-09-18",
    "img": "imakevideogames.png",
    "key": "imakevideogames",
    "title": "I make video games"
  },
  {
    "id": "2007.154",
    "date": "2007-09-18",
    "img": "iwantedthis.png",
    "key": "iwantedthis",
    "title": "I wanted this"
  },
  {
    "id": "2007.153",
    "date": "2007-09-18",
    "img": "hungryeyes.png",
    "key": "hungryeyes",
    "title": "hungry eyes"
  },
  {
    "id": "2007.152",
    "date": "2007-09-17",
    "img": "icantwaitmuchlonger.png",
    "key": "icantwaitmuchlonger",
    "title": "I can't wait much longer..."
  },
  {
    "id": "2007.151",
    "date": "2007-09-17",
    "img": "ilearnedtheirlanguagetotalktothem.png",
    "key": "ilearnedtheirlanguagetotalktothem",
    "title": "I learned their language to talk to them"
  },
  {
    "id": "2007.150",
    "date": "2007-09-17",
    "img": "imrunningoutofrope.png",
    "key": "imrunningoutofrope",
    "title": "I'm running out of rope"
  },
  {
    "id": "2007.149",
    "date": "2007-09-14",
    "img": "imgettingfatter.png",
    "key": "imgettingfatter",
    "title": "I'm getting fatter"
  },
  {
    "id": "2007.148",
    "date": "2007-09-14",
    "img": "nobodyknowsimasuperstar.png",
    "key": "nobodyknowsimasuperstar",
    "title": "nobody knows I am a superstar"
  },
  {
    "id": "2007.147",
    "date": "2007-09-13",
    "img": "iwillnotshouldonmyselftoday.png",
    "key": "iwillnotshouldonmyselftoday",
    "title": "I will not should on myself today"
  },
  {
    "id": "2007.146",
    "date": "2007-09-13",
    "img": "insideifeelreallysad.png",
    "key": "insideifeelreallysad",
    "title": "inside I feel really sad"
  },
  {
    "id": "2007.145",
    "date": "2007-09-13",
    "img": "arockinthestreamofprogress.png",
    "key": "arockinthestreamofprogress",
    "title": "A rock in the stream of progress"
  },
  {
    "id": "2007.144",
    "date": "2007-09-12",
    "img": "ionlylookatyouthroughmycamera.png",
    "key": "ionlylookatyouthroughmycamera",
    "title": "I only look at you through my camera"
  },
  {
    "id": "2007.143",
    "date": "2007-09-12",
    "img": "ihaveneverbeenhappierthanthis.png",
    "key": "ihaveneverbeenhappierthanthis",
    "title": "I have never been happier than this"
  },
  {
    "id": "2007.142",
    "date": "2007-09-12",
    "img": "ididnottalktoday.png",
    "key": "ididnottalktoday",
    "title": "I did not talk today"
  },
  {
    "id": "2007.141",
    "date": "2007-09-11",
    "img": "willibeabletodoit.png",
    "key": "willibeabletodoit",
    "title": "will I be able to do it?"
  },
  {
    "id": "2007.140",
    "date": "2007-09-11",
    "img": "justmovedin.png",
    "key": "justmovedin",
    "title": "just moved in"
  },
  {
    "id": "2007.139",
    "date": "2007-09-11",
    "img": "dogsonabeach.png",
    "key": "dogsonabeach",
    "title": "dogs on a beach"
  },
  {
    "id": "2007.138",
    "date": "2007-09-10",
    "img": "somethingstrangeishappeningallthetime.png",
    "key": "somethingstrangeishappeningallthetime",
    "title": "something strange is happening all the time"
  },
  {
    "id": "2007.137",
    "date": "2007-09-10",
    "img": "justwannahavefun.png",
    "key": "justwannahavefun",
    "title": "just wanna have fun"
  },
  {
    "id": "2007.136",
    "date": "2007-09-10",
    "img": "iwishicoulddeleteyoufrommymemory.png",
    "key": "iwishicoulddeleteyoufrommymemory",
    "title": "I wish I could delete you from my memory"
  },
  {
    "id": "2007.135",
    "date": "2007-09-07",
    "img": "sometimesimagiant.png",
    "key": "sometimesimagiant",
    "title": "sometimes I'm a giant"
  },
  {
    "id": "2007.134",
    "date": "2007-09-07",
    "img": "togetherwearespecial.png",
    "key": "togetherwearespecial",
    "title": "together we are special"
  },
  {
    "id": "2007.133",
    "date": "2007-09-06",
    "img": "howfarawayisomaha.png",
    "key": "howfarawayisomaha",
    "title": "how far away is Omaha?"
  },
  {
    "id": "2007.132",
    "date": "2007-09-06",
    "img": "idontwanttoturn30.png",
    "key": "idontwanttoturn30",
    "title": "I don't want to turn 30"
  },
  {
    "id": "2007.131",
    "date": "2007-09-05",
    "img": "collectionofthoughts.png",
    "key": "collectionofthoughts",
    "title": "collection of thoughts"
  },
  {
    "id": "2007.130",
    "date": "2007-09-05",
    "img": "iapologizedwhydoyoustillhateme.png",
    "key": "iapologizedwhydoyoustillhateme",
    "title": "I apologized, why do you still hate me?"
  },
  {
    "id": "2007.129",
    "date": "2007-09-04",
    "img": "wouldyouifyoucould.png",
    "key": "wouldyouifyoucould",
    "title": "would you if you could?"
  },
  {
    "id": "2007.128",
    "date": "2007-09-04",
    "img": "iwanttobelieveyou.png",
    "key": "iwanttobelieveyou",
    "title": "i want to believe you"
  },
  {
    "id": "2007.127",
    "date": "2007-09-04",
    "img": "acceptthatyoureoutofyourmind.png",
    "key": "acceptthatyoureoutofyourmind",
    "title": "accept that you're out of your mind"
  },
  {
    "id": "2007.126",
    "date": "2007-08-31",
    "img": "mylifeisamazingbut.png",
    "key": "mylifeisamazingbut",
    "title": "my life is amazing but im always worried about something and i dont know what it is."
  },
  {
    "id": "2007.125",
    "date": "2007-08-31",
    "img": "itwaslateandiwastired.png",
    "key": "itwaslateandiwastired",
    "title": "It was late and I was tired"
  },
  {
    "id": "2007.124",
    "date": "2007-08-30",
    "img": "doyouwantahearttinmanordoyouwantthetruth.png",
    "key": "doyouwantahearttinmanordoyouwantthetruth",
    "title": "Do you want a heart tin man, or do you want the truth?"
  },
  {
    "id": "2007.123",
    "date": "2007-08-30",
    "img": "really.png",
    "key": "really",
    "title": "really?"
  },
  {
    "id": "2007.122",
    "date": "2007-08-30",
    "img": "hewasjustforpretend.png",
    "key": "hewasjustforpretend",
    "title": "he was just for pretend"
  },
  {
    "id": "2007.121",
    "date": "2007-08-29",
    "img": "pleaseacceptthatyouarewrong.png",
    "key": "pleaseacceptthatyouarewrong",
    "title": "Please accept that you are wrong"
  },
  {
    "id": "2007.120",
    "date": "2007-08-29",
    "img": "youget3daystofeelbetter.png",
    "key": "youget3daystofeelbetter",
    "title": "you get 3 days to feel better"
  },
  {
    "id": "2007.119",
    "date": "2007-08-28",
    "img": "wouldyouhavechangedanything.png",
    "key": "wouldyouhavechangedanything",
    "title": "would you have changed anything?"
  },
  {
    "id": "2007.118",
    "date": "2007-08-28",
    "img": "itwasjustonetime.png",
    "key": "itwasjustonetime",
    "title": "it was just one time"
  },
  {
    "id": "2007.117",
    "date": "2007-08-27",
    "img": "illswimbackwards.png",
    "key": "illswimbackwards",
    "title": "I'll swim backwards"
  },
  {
    "id": "2007.116",
    "date": "2007-08-27",
    "img": "amanandaladywhoseheadlookslikealeaf.png",
    "key": "amanandaladywhoseheadlookslikealeaf",
    "title": "a man and a lady whose head looks like a leaf"
  },
  {
    "id": "2007.115",
    "date": "2007-08-27",
    "img": "itsasmallworld.png",
    "key": "itsasmallworld",
    "title": "it's a small world"
  },
  {
    "id": "2007.114",
    "date": "2007-08-24",
    "img": "birdsdontfly.png",
    "key": "birdsdontfly",
    "title": "birds don't fly"
  },
  {
    "id": "2007.113",
    "date": "2007-08-24",
    "img": "darkcolorfulandspacey.png",
    "key": "darkcolorfulandspacey",
    "title": "dark, colorful, and spacey"
  },
  {
    "id": "2007.112",
    "date": "2007-08-24",
    "img": "iamanengineer.png",
    "key": "iamanengineer",
    "title": "I am an engineer"
  },
  {
    "id": "2007.111",
    "date": "2007-08-23",
    "img": "wellnobodytoldmethat2.png",
    "key": "wellnobodytoldmethat2",
    "title": "well nobody told me that"
  },
  {
    "id": "2007.110",
    "date": "2007-08-23",
    "img": "whenigrowup.png",
    "key": "whenigrowup",
    "title": "when I grow up"
  },
  {
    "id": "2007.109",
    "date": "2007-08-22",
    "img": "arethosereal2.png",
    "key": "arethosereal",
    "title": "are those real?"
  },
  {
    "id": "2007.108",
    "date": "2007-08-22",
    "img": "areyougoingtoeatme.png",
    "key": "areyougoingtoeatme",
    "title": "are you going to eat me?"
  },
  {
    "id": "2007.107",
    "date": "2007-08-21",
    "img": "iseverythingok.png",
    "key": "iseverythingok",
    "title": "is everything ok?"
  },
  {
    "id": "2007.106",
    "date": "2007-08-21",
    "img": "itdidnthavetoendthisway2.png",
    "key": "itdidnthavetoendthisway2",
    "title": "it didn't have to end this way"
  },
  {
    "id": "2007.105",
    "date": "2007-08-20",
    "img": "imheretosellyousomething.png",
    "key": "imheretosellyousomething",
    "title": "I'm here to sell you something"
  },
  {
    "id": "2007.104",
    "date": "2007-08-20",
    "img": "timingiseverything.png",
    "key": "timingiseverything",
    "title": "timing is everything"
  },
  {
    "id": "2007.103",
    "date": "2007-08-17",
    "img": "imdepressed.png",
    "key": "imdepressed",
    "title": "I'm depressed"
  },
  {
    "id": "2007.102",
    "date": "2007-08-17",
    "img": "ineedanothercupofcoffee.png",
    "key": "ineedanothercupofcoffee",
    "title": "I need another cup of coffee"
  },
  {
    "id": "2007.101",
    "date": "2007-08-17",
    "img": "itwillbefun.png",
    "key": "itwillbefun",
    "title": "it will be fun"
  },
  {
    "id": "2007.100",
    "date": "2007-08-16",
    "img": "imlookingfortheanswer.png",
    "key": "imlookingfortheanswer",
    "title": "I'm looking for the answer"
  },
  {
    "id": "2007.99",
    "date": "2007-08-16",
    "img": "mymusic.png",
    "key": "mymusic",
    "title": "my music"
  },
  {
    "id": "2007.98",
    "date": "2007-08-15",
    "img": "todaytheworldhasbeautifulcolours.png",
    "key": "todaytheworldhasbeautifulcolours",
    "title": "today the world has beautiful colors"
  },
  {
    "id": "2007.97",
    "date": "2007-08-15",
    "img": "imbroke.png",
    "key": "imbroke",
    "title": "I'm broke"
  },
  {
    "id": "2007.96",
    "date": "2007-08-15",
    "img": "ineedtocallyourightnowandtellyouthatiloveyou.png",
    "key": "ineedtocallyourightnowandtellyouthatiloveyou",
    "title": "I need to call you right now and tell you that I love you"
  },
  {
    "id": "2007.95",
    "date": "2007-08-14",
    "img": "doesitdothateverytime.png",
    "key": "doesitdothateverytime",
    "title": "does it do that everytime?"
  },
  {
    "id": "2007.94",
    "date": "2007-08-14",
    "img": "apensivechimphavingadrinkandasmokeatabaralone.png",
    "key": "apensivechimphavingadrinkandasmokeatabaralone",
    "title": "a pensive chimp having a drink and a smoke at a bar alone"
  },
  {
    "id": "2007.93",
    "date": "2007-08-14",
    "img": "iteachmath.png",
    "key": "iteachmath",
    "title": "I teach math"
  },
  {
    "id": "2007.92",
    "date": "2007-08-13",
    "img": "heyitsjustshoes.png",
    "key": "heyitsjustshoes",
    "title": "hey, it's just shoes"
  },
  {
    "id": "2007.91",
    "date": "2007-08-13",
    "img": "weusedtobesoclosewhathappened.png",
    "key": "weusedtobesoclosewhathappened",
    "title": "we used to be so close, what happened?"
  },
  {
    "id": "2007.90",
    "date": "2007-08-13",
    "img": "thisdoesntseemright.png",
    "key": "thisdoesntseemright",
    "title": "this doesn't seem right"
  },
  {
    "id": "2007.89",
    "date": "2007-07-12",
    "img": "heretheyaredone.png",
    "key": "heretheyaredone",
    "title": "here they are done"
  },
  {
    "id": "2007.88",
    "date": "2007-07-12",
    "img": "dontstop.jpg",
    "key": "dontstop",
    "title": "don't stop"
  },
  {
    "id": "2007.87",
    "date": "2007-07-12",
    "img": "iaminlove.png",
    "key": "iaminlove",
    "title": "I am in love"
  },
  {
    "id": "2007.86",
    "date": "2007-07-12",
    "img": "wowthisisfun.png",
    "key": "wowthisisfun",
    "title": "wow this is fun...."
  },
  {
    "id": "2007.85",
    "date": "2007-07-09",
    "img": "heditit.png",
    "key": "heditit",
    "title": "he did it"
  },
  {
    "id": "2007.84",
    "date": "2007-07-09",
    "img": "itonlyworksintheory.png",
    "key": "itonlyworksintheory",
    "title": "It only works in theory"
  },
  {
    "id": "2007.83",
    "date": "2007-06-28",
    "img": "waitingforsummer.png",
    "key": "waitingforsummer",
    "title": "waiting for summer"
  },
  {
    "id": "2007.82",
    "date": "2007-06-28",
    "img": "hetoldmetodoit.png",
    "key": "hetoldmetodoit",
    "title": "HE TOLD ME TO DO IT!!!!"
  },
  {
    "id": "2007.81",
    "date": "2007-06-28",
    "img": "ineedtobeoutside.png",
    "key": "ineedtobeoutside",
    "title": "I need to be outside"
  },
  {
    "id": "2007.80",
    "date": "2007-06-27",
    "img": "iwasscaredtocallbutidid.png",
    "key": "iwasscaredtocallbutidid",
    "title": "I was scared to call but I did"
  },
  {
    "id": "2007.79",
    "date": "2007-06-27",
    "img": "iworkinamuseum.png",
    "key": "iworkinamuseum",
    "title": "I work in a museum"
  },
  {
    "id": "2007.78",
    "date": "2007-06-27",
    "img": "ilovethissong.png",
    "key": "ilovethissong",
    "title": "i love this song"
  },
  {
    "id": "2007.77",
    "date": "2007-06-25",
    "img": "itwasneverlikethis.png",
    "key": "itwasneverlikethis",
    "title": "it was never like this"
  },
  {
    "id": "2007.76",
    "date": "2007-06-25",
    "img": "ithinkyouunderstand.png",
    "key": "ithinkyouunderstand",
    "title": "I think you understand"
  },
  {
    "id": "2007.75",
    "date": "2007-06-20",
    "img": "thatmeansnothingtomenow.png",
    "key": "thatmeansnothingtomenow",
    "title": "that means nothing to me now"
  },
  {
    "id": "2007.74",
    "date": "2007-06-20",
    "img": "istilldontunderstand.png",
    "key": "istilldontunderstand",
    "title": "I still don't understand"
  },
  {
    "id": "2007.73",
    "date": "2007-06-19",
    "img": "youhaveimprovedmyqualityofl.png",
    "key": "youhaveimprovedmyqualityofl",
    "title": "you have improved my quality of life"
  },
  {
    "id": "2007.72",
    "date": "2007-06-19",
    "img": "ijustquitmyjob.png",
    "key": "ijustquitmyjob",
    "title": "I just quit my job"
  },
  {
    "id": "2007.71",
    "date": "2007-06-19",
    "img": "icantitstoostupid.png",
    "key": "icantitstoostupid",
    "title": "I can't it's too stupid"
  },
  {
    "id": "2007.70",
    "date": "2007-06-15",
    "img": "whycantistoplovingyou.png",
    "key": "whycantistoplovingyou",
    "title": "Why can't I stop loving you?"
  },
  {
    "id": "2007.69",
    "date": "2007-06-15",
    "img": "comeintomytimemachine.png",
    "key": "comeintomytimemachine",
    "title": "do you want a ride in my time machine"
  },
  {
    "id": "2007.68",
    "date": "2007-06-14",
    "img": "hereiambeingpatient.png",
    "key": "hereiambeingpatient",
    "title": "Here I am being patient"
  },
  {
    "id": "2007.67",
    "date": "2007-06-14",
    "img": "youknowyoucantdothathere.png",
    "key": "youknowyoucantdothathere",
    "title": "You know you can't do that here"
  },
  {
    "id": "2007.66",
    "date": "2007-06-12",
    "img": "toolatetoturnbacknow.png",
    "key": "toolatetoturnbacknow",
    "title": "too late to turn back now"
  },
  {
    "id": "2007.65",
    "date": "2007-06-12",
    "img": "itsallintheeyes.png",
    "key": "itsallintheeyes",
    "title": "it's all in the eyes"
  },
  {
    "id": "2007.64",
    "date": "2007-06-12",
    "img": "whoareyou.png",
    "key": "whoareyou",
    "title": "who are you?"
  },
  {
    "id": "2007.63",
    "date": "2007-06-12",
    "img": "doyouthinkyoucoulddrawmeaze.png",
    "key": "doyouthinkyoucoulddrawmeaze",
    "title": "do you think you could draw me a zebra?"
  },
  {
    "id": "2007.62",
    "date": "2007-06-12",
    "img": "ineedafreshstart.png",
    "key": "ineedafreshstart",
    "title": "I need a fresh start"
  },
  {
    "id": "2007.61",
    "date": "2007-06-06",
    "img": "whateverhappenedtoyou-.png",
    "key": "whateverhappenedtoyou-",
    "title": "Whatever happened to you"
  },
  {
    "id": "2007.60",
    "date": "2007-06-06",
    "img": "whycantyoujustdisappear.png",
    "key": "whycantyoujustdisappear",
    "title": "why can't you just disappear"
  },
  {
    "id": "2007.59",
    "date": "2007-06-06",
    "img": "areyouevergoingtogetitright.png",
    "key": "areyouevergoingtogetitright",
    "title": "are you ever going to get it right"
  },
  {
    "id": "2007.58",
    "date": "2007-06-06",
    "img": "notme.png",
    "key": "notme",
    "title": "not me"
  },
  {
    "id": "2007.57",
    "date": "2007-06-04",
    "img": "ducksareeatingmybrain.png",
    "key": "ducksareeatingmybrain",
    "title": "ducks are eating my brain"
  },
  {
    "id": "2007.56",
    "date": "2007-06-04",
    "img": "newzealandisveryfaraway.png",
    "key": "newzealandisveryfaraway",
    "title": "New Zealand is very far away"
  },
  {
    "id": "2007.55",
    "date": "2007-05-30",
    "img": "imgettingtired.png",
    "key": "imgettingtired",
    "title": "I'm getting tired"
  },
  {
    "id": "2007.54",
    "date": "2007-05-30",
    "img": "icantmakeyouthinkofme.png",
    "key": "icantmakeyouthinkofme",
    "title": "I can't make you think of me"
  },
  {
    "id": "2007.53",
    "date": "2007-05-08",
    "img": "iwanttotellyoueverything.png",
    "key": "iwanttotellyoueverything",
    "title": "I want to tell you every thing"
  },
  {
    "id": "2007.52",
    "date": "2007-05-08",
    "img": "ifeelsoheavy.png",
    "key": "ifeelsoheavy",
    "title": "I feel so heavy"
  },
  {
    "id": "2007.51",
    "date": "2007-05-04",
    "img": "isittoolateortooearly.png",
    "key": "isittoolateortooearly",
    "title": "is it too late or too early"
  },
  {
    "id": "2007.50",
    "date": "2007-05-04",
    "img": "thecitymakesmefeelbig2.png",
    "key": "thecitymakesmefeelbig2",
    "title": "the city makes me feel big"
  },
  {
    "id": "2007.49",
    "date": "2007-05-04",
    "img": "pardonmeineedtosavemyself.png",
    "key": "pardonmeineedtosavemyself",
    "title": "Pardon me, I need to save myself"
  },
  {
    "id": "2007.48",
    "date": "2007-05-03",
    "img": "iliketodance.png",
    "key": "iliketodance",
    "title": "I like to dance"
  },
  {
    "id": "2007.47",
    "date": "2007-05-03",
    "img": "ihopeyoufeelbettersoon.png",
    "key": "ihopeyoufeelbettersoon",
    "title": "I hope you feel better soon"
  },
  {
    "id": "2007.46",
    "date": "2007-05-01",
    "img": "awesomeness.png",
    "key": "awesomeness",
    "title": "awesomeness"
  },
  {
    "id": "2007.45",
    "date": "2007-05-01",
    "img": "igottoheaven.png",
    "key": "igottoheaven",
    "title": "I got to heaven"
  },
  {
    "id": "2007.44",
    "date": "2007-05-01",
    "img": "butbaby.png",
    "key": "butbaby",
    "title": "but, baby i love you"
  },
  {
    "id": "2007.43",
    "date": "2007-04-30",
    "img": "itsnottheroadiamon.png",
    "key": "itsnottheroadiamon",
    "title": "it's not the road I am on"
  },
  {
    "id": "2007.42",
    "date": "2007-04-30",
    "img": "lunchpunch.png",
    "key": "lunchpunch",
    "title": "LUNCH PUNCH"
  },
  {
    "id": "2007.41",
    "date": "2007-04-30",
    "img": "possibilities2.png",
    "key": "possibilities2",
    "title": "possibilities"
  },
  {
    "id": "2007.40",
    "date": "2007-04-25",
    "img": "ifoundit.png",
    "key": "ifoundit",
    "title": "I found it"
  },
  {
    "id": "2007.39",
    "date": "2007-04-25",
    "img": "wellnevermakeit.png",
    "key": "wellnevermakeit",
    "title": "We'll never make it"
  },
  {
    "id": "2007.38",
    "date": "2007-04-25",
    "img": "thatdogsmells.png",
    "key": "thatdogsmells",
    "title": "that dog smells"
  },
  {
    "id": "2007.37",
    "date": "2007-04-24",
    "img": "wehavetowakeupsoon.png",
    "key": "wehavetowakeupsoon",
    "title": "we have to wake up soon"
  },
  {
    "id": "2007.36",
    "date": "2007-04-24",
    "img": "itsmuchlesscrowdedontheinside.png",
    "key": "itsmuchlesscrowdedontheinside",
    "title": "it's much less crowded on the inside"
  },
  {
    "id": "2007.35",
    "date": "2007-04-24",
    "img": "thecatneedsajob.png",
    "key": "thecatneedsajob",
    "title": "the cat needs a job"
  },
  {
    "id": "2007.34",
    "date": "2007-04-16",
    "img": "willyouevercomeback-.png",
    "key": "willyouevercomeback-",
    "title": "will you ever come back?"
  },
  {
    "id": "2007.33",
    "date": "2007-04-16",
    "img": "itwasfunwhileitlasted.png",
    "key": "itwasfunwhileitlasted",
    "title": "It was fun while it lasted"
  },
  {
    "id": "2007.32",
    "date": "2007-04-16",
    "img": "funrollercoaster.png",
    "key": "funrollercoaster",
    "title": "Fun roller coaster"
  },
  {
    "id": "2007.31",
    "date": "2007-03-28",
    "img": "ohnoidroppedit.png",
    "key": "ohnoidroppedit",
    "title": "oh no, I dropped it"
  },
  {
    "id": "2007.30",
    "date": "2007-03-28",
    "img": "iminthisforthelonghaul.png",
    "key": "iminthisforthelonghaul",
    "title": "I'm in this for the long haul"
  },
  {
    "id": "2007.29",
    "date": "2007-03-07",
    "img": "idontgetit.png",
    "key": "idontgetit",
    "title": "I don't get it"
  },
  {
    "id": "2007.28",
    "date": "2007-03-07",
    "img": "imjustnothungry.png",
    "key": "imjustnothungry",
    "title": "I'm just not hungry"
  },
  {
    "id": "2007.27",
    "date": "2007-02-06",
    "img": "everythingisachoice.png",
    "key": "everythingisachoice",
    "title": "everything is a choice"
  },
  {
    "id": "2007.26",
    "date": "2007-02-06",
    "img": "itsjustme.png",
    "key": "itsjustme",
    "title": "it's just me"
  },
  {
    "id": "2007.25",
    "date": "2007-02-06",
    "img": "issheoutthere.png",
    "key": "issheoutthere",
    "title": "is she out there?"
  },
  {
    "id": "2007.24",
    "date": "2007-01-29",
    "img": "icanttellmybestfriendyet.png",
    "key": "icanttellmybestfriendyet",
    "title": "I can't tell my best friend yet"
  },
  {
    "id": "2007.23",
    "date": "2007-01-29",
    "img": "bydawnwewillbegone.png",
    "key": "bydawnwewillbegone",
    "title": "by dawn we will be gone"
  },
  {
    "id": "2007.22",
    "date": "2007-01-29",
    "img": "stillglowing.png",
    "key": "stillglowing",
    "title": "still glowing"
  },
  {
    "id": "2007.21",
    "date": "2007-01-29",
    "img": "letsgetiton.png",
    "key": "letsgetiton",
    "title": "let's get it on"
  },
  {
    "id": "2007.20",
    "date": "2007-01-26",
    "img": "itisallgoingby3.png",
    "key": "itisallgoingby3",
    "title": "it is all going by"
  },
  {
    "id": "2007.19",
    "date": "2007-01-26",
    "img": "igetsonervous.png",
    "key": "igetsonervous",
    "title": "i get so nervous"
  },
  {
    "id": "2007.18",
    "date": "2007-01-23",
    "img": "illgetthereeventually.png",
    "key": "illgetthereeventually",
    "title": "i'll get there eventually"
  },
  {
    "id": "2007.17",
    "date": "2007-01-23",
    "img": "idontknowyoubutiwillmissyou.png",
    "key": "idontknowyoubutiwillmissyou",
    "title": "I don't know you but I will miss you"
  },
  {
    "id": "2007.16",
    "date": "2007-01-23",
    "img": "iloveyoubuticant.png",
    "key": "iloveyoubuticant",
    "title": "I love you but I can't stand being near you"
  },
  {
    "id": "2007.15",
    "date": "2007-01-18",
    "img": "itsnotaboutjustyou.png",
    "key": "itisnotaboutjustyou",
    "title": "it is not about just you"
  },
  {
    "id": "2007.14",
    "date": "2007-01-18",
    "img": "itsmybrain.png",
    "key": "itsmybrain",
    "title": "it's my brain"
  },
  {
    "id": "2007.13",
    "date": "2007-01-12",
    "img": "lifeiscomplicated.png",
    "key": "lifeiscomplicated",
    "title": "life is complicated"
  },
  {
    "id": "2007.12",
    "date": "2007-01-12",
    "img": "nevergiveup.png",
    "key": "nevergiveup",
    "title": "never give up"
  },
  {
    "id": "2007.11",
    "date": "2007-01-12",
    "img": "itisworsethanithought.png",
    "key": "itisworsethanithought",
    "title": "it is worse than i thought"
  },
  {
    "id": "2007.10",
    "date": "2007-01-08",
    "img": "openyoureyesyouare.png",
    "key": "openyoureyesyouare",
    "title": "open your eyes! you are being lied to"
  },
  {
    "id": "2007.9",
    "date": "2007-01-08",
    "img": "thisiseverything.png",
    "key": "thisiseverything",
    "title": "this is everything"
  },
  {
    "id": "2007.8",
    "date": "2007-01-05",
    "img": "sosadtogoback.png",
    "key": "sosadtogoback",
    "title": "so sad to go back"
  },
  {
    "id": "2007.7",
    "date": "2007-01-05",
    "img": "ourlifeisabouttochangeforever.png",
    "key": "ourlifeisabouttochangeforever",
    "title": "our life is about to change forever"
  },
  {
    "id": "2007.6",
    "date": "2007-01-05",
    "img": "timewillneverstop.png",
    "key": "timewillneverstop",
    "title": "time will never stop"
  },
  {
    "id": "2007.5",
    "date": "2007-01-05",
    "img": "wewerealwaysthebestoffriends.png",
    "key": "wewerealwaysthebestoffriends",
    "title": "we were always the best of friends"
  },
  {
    "id": "2007.4",
    "date": "2007-01-04",
    "img": "wehavenotbeenhereforawhile.png",
    "key": "wehavenotbeenhereforawhile",
    "title": "we have not been here for a while"
  },
  {
    "id": "2007.3",
    "date": "2007-01-04",
    "img": "theywillneverknow.png",
    "key": "theywillneverknow",
    "title": "they will never know"
  },
  {
    "id": "2007.2",
    "date": "2007-01-02",
    "img": "ourwordswillnotsaveyou.png",
    "key": "ourwordswillnotsaveyou",
    "title": "our words will not save you"
  },
  {
    "id": "2007.1",
    "date": "2007-01-02",
    "img": "youknowidontthink.png",
    "key": "youknowidontthink",
    "title": "You know, I don't think that was here before..."
  }
]
